roll_cli/__init__.py
roll_cli/__main__.py
roll_cli/parser/__init__.py
roll_cli/parser/diceparser.py
roll_cli/parser/operations.py
roll_cli/parser/types/__init__.py
roll_cli/parser/types/evaluationresults.py
roll_cli/parser/types/rolloption.py
roll_cli/parser/types/rollresults.py
roll_cli/py.typed
roll_cli/roll.py
roll_cli-2.0.0.dist-info/entry_points.txt
roll_cli-2.0.0.dist-info/LICENSE.rst
roll_cli-2.0.0.dist-info/LICENSE.txt
roll_cli-2.0.0.dist-info/WHEEL
roll_cli-2.0.0.dist-info/METADATA
roll_cli-2.0.0.dist-info/RECORD
