Metadata-Version: 2.1
Name: roll-cli
Version: 2.0.0
Summary: Dice roller with all of the features you could want.
Home-page: https://github.com/vlek/roll-cli
License: GPL-3.0
Keywords: dice,die,roll,rolling,game,gaming,rp,rpg,parse,parser,parsing,cli,terminal
Author: Derek McCammond
Author-email: derek.mccammond@protonmail.com
Requires-Python: >=3.7,<4.0
Classifier: Development Status :: 5 - Production/Stable
Classifier: License :: OSI Approved :: GNU General Public License v3 (GPLv3)
Classifier: Programming Language :: Python :: 3
Classifier: Programming Language :: Python :: 3.10
Classifier: Programming Language :: Python :: 3.7
Classifier: Programming Language :: Python :: 3.8
Classifier: Programming Language :: Python :: 3.9
Requires-Dist: click (>=8.0.1,<9.0.0)
Requires-Dist: pyparsing (>=3.0.7,<4.0.0)
Project-URL: Changelog, https://github.com/vlek/roll-cli/releases
Project-URL: Documentation, https://roll-cli.readthedocs.io
Project-URL: Repository, https://github.com/vlek/roll-cli
